kauai/__about__.py
kauai/__init__.py
kauai-1.0.dist-info/METADATA
kauai-1.0.dist-info/WHEEL
kauai-1.0.dist-info/entry_points.txt
kauai-1.0.dist-info/licenses/LICENSE.txt
kauai-1.0.dist-info/RECORD
